finolog/__init__.py
finolog/_version.py
finolog/client.py
finolog/exceptions.py
finolog/utils.py
finolog/services/__init__.py
finolog/services/api_service.py
finolog/services/contractor_service.py
finolog/services/country_service.py
finolog/services/document_service.py
finolog/services/requisite_service.py
finolog/types/__init__.py
finolog/types/contractor_types.py
finolog/types/country_types.py
finolog/types/document_types.py
finolog/types/requisite_types.py
finolog_sdk-1.0.6.5.dist-info/METADATA
finolog_sdk-1.0.6.5.dist-info/WHEEL
finolog_sdk-1.0.6.5.dist-info/top_level.txt
finolog_sdk-1.0.6.5.dist-info/RECORD
